bitpy/__init__.py
bitpy/bitpy.py
bitpy-1.44.dist-info/LICENSE
bitpy-1.44.dist-info/METADATA
bitpy-1.44.dist-info/WHEEL
bitpy-1.44.dist-info/top_level.txt
bitpy-1.44.dist-info/RECORD
