Metadata-Version: 2.1
Name: bitpy
Version: 1.44
Summary: BitPy
Author: Philippe Remy
License-File: LICENSE
Requires-Dist: numpy
Requires-Dist: pandas
Requires-Dist: websocket-client
Requires-Dist: requests
Requires-Dist: urllib3
Requires-Dist: orjson
Requires-Dist: pybit
